README.md
setup.py
etab/__init__.py
etab/datasets.py
etab.egg-info/PKG-INFO
etab.egg-info/SOURCES.txt
etab.egg-info/dependency_links.txt
etab.egg-info/requires.txt
etab.egg-info/top_level.txt